GMAT_app/GMAT.py
GMAT_app/user.txt
Prep_GMAT_tool_emialex-1.2.1.dist-info/METADATA
Prep_GMAT_tool_emialex-1.2.1.dist-info/WHEEL
Prep_GMAT_tool_emialex-1.2.1.dist-info/entry_points.txt
Prep_GMAT_tool_emialex-1.2.1.dist-info/top_level.txt
Prep_GMAT_tool_emialex-1.2.1.dist-info/RECORD
