Metadata-Version: 2.1
Name: Prep-GMAT-tool-emialex
Version: 1.2.1
Summary: access questions relating to GMAT
Home-page: https://github.com/emialex
Author: emi alex
Author-email: 
License: UNKNOWN
Platform: UNKNOWN
Requires-Dist: requests
